{
   "Favorites":[
      {
         "CategoryId":"codwaw",
         "ModId":188,
         "Name":"Physics 'n' Flex Menu",
         "Message":"",
         "ImageUrl":"",
         "Platform":"PS3"
      },
      {
         "CategoryId":"codbo",
         "ModId":251,
         "Name":"Jo-Milk's Playground",
         "Message":"",
         "ImageUrl":"",
         "Platform":"PS3"
      },
      {
         "CategoryId":"codmw2",
         "ModId":348,
         "Name":"Reborn Menu (Cracked)",
         "Message":"",
         "ImageUrl":"",
         "Platform":"PS3"
      },
      {
         "CategoryId":"codbo2",
         "ModId":362,
         "Name":"Infracted Menu",
         "Message":"",
         "ImageUrl":"",
         "Platform":"PS3"
      },
      {
         "CategoryId":"codmw3",
         "ModId":79,
         "Name":"Menace Menu",
         "Message":"",
         "ImageUrl":"",
         "Platform":"PS3"
      },
      {
         "CategoryId":"codghosts",
         "ModId":379,
         "Name":"Kebab Engine",
         "Message":"",
         "ImageUrl":"",
         "Platform":"PS3"
      },
      {
         "CategoryId":"codghosts",
         "ModId":379,
         "Name":"Kebab Engine",
         "Message":"",
         "ImageUrl":"",
         "Platform":"PS3"
      },
      {
         "CategoryId":"gta5",
         "ModId":37,
         "Name":"Tgsaudoiz Mod Loader",
         "Message":"",
         "ImageUrl":"",
         "Platform":"PS3"
      },
      {
         "CategoryId":"bf4",
         "ModId":116,
         "Name":"The Outcast Menu",
         "Message":"",
         "ImageUrl":"",
         "Platform":"PS3"
      },
      {
         "CategoryId":"gta5",
         "ModId":12,
         "Name":"Ghost Menu",
         "Message":"",
         "ImageUrl":"",
         "Platform":"XBOX"
      },
      {
         "CategoryId":"gta5",
         "ModId":9,
         "Name":"El Host Menu",
         "Message":"",
         "ImageUrl":"",
         "Platform":"XBOX"
      },
      {
         "CategoryId":"gta5",
         "ModId":5,
         "Name":"Afrikans Menu (Cracked)",
         "Message":"",
         "ImageUrl":"",
         "Platform":"XBOX"
      },
      {
         "CategoryId":"codmw3",
         "ModId":35,
         "Name":"Velonia Menu",
         "Message":"",
         "ImageUrl":"",
         "Platform":"XBOX"
      },
      {
         "CategoryId":"codbo2",
         "ModId":41,
         "Name":"Appendum Menu",
         "Message":"",
         "ImageUrl":"",
         "Platform":"XBOX"
      },
      {
         "CategoryId":"codbo",
         "ModId":47,
         "Name":"Revival Project Menu",
         "Message":"",
         "ImageUrl":"",
         "Platform":"XBOX"
      }
   ]
}
